orcaz/NiftiDataset.py
orcaz/__init__.py
orcaz/config.py
orcaz/constants.py
orcaz/discriminators.py
orcaz/display.py
orcaz/download.py
orcaz/file_utilities.py
orcaz/generators.py
orcaz/image_conversion.py
orcaz/image_processing.py
orcaz/input_validation.py
orcaz/options.py
orcaz/orcaz.py
orcaz/plot_generated_batch.py
orcaz/predict_single_image.py
orcaz/registration.py
orcaz/resources.py
orcaz/settings.py
orcaz/showcase.py
orcaz/train.py
orcaz/train_utils.py
orcaz-0.1.5.dist-info/LICENSE
orcaz-0.1.5.dist-info/METADATA
orcaz-0.1.5.dist-info/WHEEL
orcaz-0.1.5.dist-info/entry_points.txt
orcaz-0.1.5.dist-info/top_level.txt
orcaz-0.1.5.dist-info/RECORD
